botbrigade_llm/__init__.py
botbrigade_llm/client.py
botbrigade_llm-0.2.0.dist-info/licenses/LICENSE
botbrigade_llm-0.2.0.dist-info/METADATA
botbrigade_llm-0.2.0.dist-info/WHEEL
botbrigade_llm-0.2.0.dist-info/top_level.txt
botbrigade_llm-0.2.0.dist-info/RECORD
