Metadata-Version: 2.4
Name: botbrigade-llm
Version: 0.2.0
Summary: A Python SDK for interacting with the BotBrigade LLM API.
Home-page: https://github.com/bot-brigade-studio/botbrigade-llm
Author: Lantip
Author-email: lantip@gmail.com
Classifier: Programming Language :: Python :: 3
Classifier: License :: OSI Approved :: MIT License
Classifier: Operating System :: OS Independent
Requires-Python: >=3.7
License-File: LICENSE
Requires-Dist: httpx
Dynamic: author
Dynamic: author-email
Dynamic: classifier
Dynamic: description
Dynamic: description-content-type
Dynamic: home-page
Dynamic: license-file
Dynamic: requires-dist
Dynamic: requires-python
Dynamic: summary
